seqshannon/__init__.py
seqshannon/seqshannon.py
seqshannon-1.0.0.dist-info/LICENSE
seqshannon-1.0.0.dist-info/METADATA
seqshannon-1.0.0.dist-info/WHEEL
seqshannon-1.0.0.dist-info/entry_points.txt
seqshannon-1.0.0.dist-info/top_level.txt
seqshannon-1.0.0.dist-info/RECORD
