Metadata-Version: 2.1
Name: seqshannon
Version: 1.0.0
Summary: Calculate shannon entropy of biological sequences
Home-page: https://github.com/WojDob/SeqShannon
Author: Wojciech Dobrychłop
Author-email: wojciech.dobrychlop@gmail.com
Keywords: python,bioinformatics,shannon entropy,sequence analysis
Classifier: Development Status :: 3 - Alpha
Classifier: Intended Audience :: Science/Research
Classifier: License :: OSI Approved :: MIT License
Classifier: Programming Language :: Python :: 3.8
Classifier: Programming Language :: Python :: 3.9
Classifier: Programming Language :: Python :: 3.10
License-File: LICENSE
Requires-Dist: biopython
